Aligner.cpython-312-x86_64-linux-gnu.so
weightedAlign/__init__.py
weighted_align-1.2.1.dist-info/METADATA
weighted_align-1.2.1.dist-info/WHEEL
weighted_align-1.2.1.dist-info/top_level.txt
weighted_align-1.2.1.dist-info/RECORD
