Metadata-Version: 2.1
Name: weighted_align
Version: 1.2.1
Summary: A tool for aligning DNA or marker seq.
Home-page: https://github.com/CycloneSEQ-Bioinformatics/Weighted_Align.git
Author: Junyi He
Author-email: guilitianya@126.com
Classifier: Programming Language :: Python :: 3
Classifier: License :: OSI Approved :: MIT License
Requires-Python: >=3.6
Requires-Dist: numpy
